[
    {
        "anoMes": 202301,
        "codigoPessoa": "73.972.002/0003-88",
        "nomePessoa": "BRFIBRA TELECOMUNICACOES LTDA",
        "tipoPessoa": "Entidades Empresariais Privadas",
        "municipioPessoa": "S\u00c3O PAULO",
        "siglaUFPessoa": "SP",
        "codigoUG": "242160",
        "nomeUG": "TELECOMUNICACOES BRASILEIRAS S/A",
        "codigoOrgao": "24216",
        "nomeOrgao": "Telecomunica\u00e7\u00f5es Brasileiras S.A.",
        "codigoOrgaoSuperior": "41000",
        "nomeOrgaoSuperior": "Minist\u00e9rio das Comunica\u00e7\u00f5es",
        "valor": 1770.59
    },
    {
        "anoMes": 202301,
        "codigoPessoa": "90.347.840/0003-80",
        "nomePessoa": "TK ELEVADORES BRASIL LTDA",
        "tipoPessoa": "Entidades Empresariais Privadas",
        "municipioPessoa": "S\u00c3O PAULO",
        "siglaUFPessoa": "SP",
        "codigoUG": "413001",
        "nomeUG": "AGENCIA NACIONAL DE TELECOMUNICACOES-SEDE",
        "codigoOrgao": "41231",
        "nomeOrgao": "Ag\u00eancial Nacional de Telecomunica\u00e7\u00f5es",
        "codigoOrgaoSuperior": "41000",
        "nomeOrgaoSuperior": "Minist\u00e9rio das Comunica\u00e7\u00f5es",
        "valor": 26070.0
    },
    {
        "anoMes": 202301,
        "codigoPessoa": "82.743.287/0035-53",
        "nomePessoa": "SCHNEIDER ELECTRIC BRASIL LTDA",
        "tipoPessoa": "Entidades Empresariais Privadas",
        "municipioPessoa": "CAJAMAR",
        "siglaUFPessoa": "SP",
        "codigoUG": "242160",
        "nomeUG": "TELECOMUNICACOES BRASILEIRAS S/A",
        "codigoOrgao": "24216",
        "nomeOrgao": "Telecomunica\u00e7\u00f5es Brasileiras S.A.",
        "codigoOrgaoSuperior": "41000",
        "nomeOrgaoSuperior": "Minist\u00e9rio das Comunica\u00e7\u00f5es",
        "valor": 12396.96
    },
    {
        "anoMes": 202301,
        "codigoPessoa": "57.142.978/0001-05",
        "nomePessoa": "BRASOFTWARE INFORMATICA LTDA",
        "tipoPessoa": "Entidades Empresariais Privadas",
        "municipioPessoa": "PO\u00c1",
        "siglaUFPessoa": "SP",
        "codigoUG": "410003",
        "nomeUG": "COORDENACAO-GERAL DE RECURSOS LOGISTICOS",
        "codigoOrgao": "41000",
        "nomeOrgao": "Minist\u00e9rio das Comunica\u00e7\u00f5es - Unidades com v\u00ednculo direto",
        "codigoOrgaoSuperior": "41000",
        "nomeOrgaoSuperior": "Minist\u00e9rio das Comunica\u00e7\u00f5es",
        "valor": 166244.2
    },
    {
        "anoMes": 202301,
        "codigoPessoa": "***.132.586-**",
        "nomePessoa": "MAURO ROBERTO DA CUNHA",
        "tipoPessoa": "Pessoa F\u00edsica",
        "municipioPessoa": "FRANCA",
        "siglaUFPessoa": "SP",
        "codigoUG": "242160",
        "nomeUG": "TELECOMUNICACOES BRASILEIRAS S/A",
        "codigoOrgao": "24216",
        "nomeOrgao": "Telecomunica\u00e7\u00f5es Brasileiras S.A.",
        "codigoOrgaoSuperior": "41000",
        "nomeOrgaoSuperior": "Minist\u00e9rio das Comunica\u00e7\u00f5es",
        "valor": 3442.93
    },
    {
        "anoMes": 202301,
        "codigoPessoa": "02.558.157/0001-62",
        "nomePessoa": "TELEFONICA BRASIL S.A.",
        "tipoPessoa": "Entidades Empresariais Privadas",
        "municipioPessoa": "S\u00c3O PAULO",
        "siglaUFPessoa": "SP",
        "codigoUG": "242160",
        "nomeUG": "TELECOMUNICACOES BRASILEIRAS S/A",
        "codigoOrgao": "24216",
        "nomeOrgao": "Telecomunica\u00e7\u00f5es Brasileiras S.A.",
        "codigoOrgaoSuperior": "41000",
        "nomeOrgaoSuperior": "Minist\u00e9rio das Comunica\u00e7\u00f5es",
        "valor": 46.1
    },
    {
        "anoMes": 202301,
        "codigoPessoa": "87.118.386/0003-80",
        "nomePessoa": "JCDECAUX MIDIA AEROPORTOS LTDA.",
        "tipoPessoa": "Entidades Empresariais Privadas",
        "municipioPessoa": "GUARULHOS",
        "siglaUFPessoa": "SP",
        "codigoUG": "410061",
        "nomeUG": "SECRETARIA ESPECIAL DE COMUNICACAO SOCIAL",
        "codigoOrgao": "41000",
        "nomeOrgao": "Minist\u00e9rio das Comunica\u00e7\u00f5es - Unidades com v\u00ednculo direto",
        "codigoOrgaoSuperior": "41000",
        "nomeOrgaoSuperior": "Minist\u00e9rio das Comunica\u00e7\u00f5es",
        "valor": 8379.0
    },
    {
        "anoMes": 202301,
        "codigoPessoa": "18.697.295/0001-62",
        "nomePessoa": "MS TELECOM SERVICES LTDA",
        "tipoPessoa": "Entidades Empresariais Privadas",
        "municipioPessoa": "BARUERI",
        "siglaUFPessoa": "SP",
        "codigoUG": "413003",
        "nomeUG": "AGENCIA NACIONAL DE TELECOMUNICACOES-RJ",
        "codigoOrgao": "41231",
        "nomeOrgao": "Ag\u00eancial Nacional de Telecomunica\u00e7\u00f5es",
        "codigoOrgaoSuperior": "41000",
        "nomeOrgaoSuperior": "Minist\u00e9rio das Comunica\u00e7\u00f5es",
        "valor": 24651.43
    },
    {
        "anoMes": 202301,
        "codigoPessoa": "26.241.737/0001-90",
        "nomePessoa": "STAEFA CONTROL SYSTEM LTDA",
        "tipoPessoa": "Entidades Empresariais Privadas",
        "municipioPessoa": "S\u00c3O BERNARDO DO CAMPO",
        "siglaUFPessoa": "SP",
        "codigoUG": "413001",
        "nomeUG": "AGENCIA NACIONAL DE TELECOMUNICACOES-SEDE",
        "codigoOrgao": "41231",
        "nomeOrgao": "Ag\u00eancial Nacional de Telecomunica\u00e7\u00f5es",
        "codigoOrgaoSuperior": "41000",
        "nomeOrgaoSuperior": "Minist\u00e9rio das Comunica\u00e7\u00f5es",
        "valor": 4241.77
    },
    {
        "anoMes": 202301,
        "codigoPessoa": "***.754.048-**",
        "nomePessoa": "THIAGO VIANA DA SILVA",
        "tipoPessoa": "Pessoa F\u00edsica",
        "municipioPessoa": "S\u00c3O PAULO",
        "siglaUFPessoa": "SP",
        "codigoUG": "413002",
        "nomeUG": "AGENCIA NACIONAL DE TELECOMUNICACOES-SP",
        "codigoOrgao": "41231",
        "nomeOrgao": "Ag\u00eancial Nacional de Telecomunica\u00e7\u00f5es",
        "codigoOrgaoSuperior": "41000",
        "nomeOrgaoSuperior": "Minist\u00e9rio das Comunica\u00e7\u00f5es",
        "valor": 1249.95
    },
    {
        "anoMes": 202301,
        "codigoPessoa": "02.998.611/0001-04",
        "nomePessoa": "CTEEP - COMPANHIA DE TRANSMISSAO DE ENERGIA ELETRICA PAULISTA",
        "tipoPessoa": "Entidades Empresariais Privadas",
        "municipioPessoa": "S\u00c3O PAULO",
        "siglaUFPessoa": "SP",
        "codigoUG": "242160",
        "nomeUG": "TELECOMUNICACOES BRASILEIRAS S/A",
        "codigoOrgao": "24216",
        "nomeOrgao": "Telecomunica\u00e7\u00f5es Brasileiras S.A.",
        "codigoOrgaoSuperior": "41000",
        "nomeOrgaoSuperior": "Minist\u00e9rio das Comunica\u00e7\u00f5es",
        "valor": 7207.01
    },
    {
        "anoMes": 202301,
        "codigoPessoa": "***.739.927-**",
        "nomePessoa": "HUMBERTO BARBOSA VINAGRE",
        "tipoPessoa": "Pessoa F\u00edsica",
        "municipioPessoa": "RIBEIR\u00c3O PRETO",
        "siglaUFPessoa": "SP",
        "codigoUG": "413002",
        "nomeUG": "AGENCIA NACIONAL DE TELECOMUNICACOES-SP",
        "codigoOrgao": "41231",
        "nomeOrgao": "Ag\u00eancial Nacional de Telecomunica\u00e7\u00f5es",
        "codigoOrgaoSuperior": "41000",
        "nomeOrgaoSuperior": "Minist\u00e9rio das Comunica\u00e7\u00f5es",
        "valor": 129.63
    },
    {
        "anoMes": 202301,
        "codigoPessoa": "01.369.056/0001-80",
        "nomePessoa": "SYS MANAGER INFORMATICA LTDA.",
        "tipoPessoa": "Entidades Empresariais Privadas",
        "municipioPessoa": "S\u00c3O CAETANO DO SUL",
        "siglaUFPessoa": "SP",
        "codigoUG": "413001",
        "nomeUG": "AGENCIA NACIONAL DE TELECOMUNICACOES-SEDE",
        "codigoOrgao": "41231",
        "nomeOrgao": "Ag\u00eancial Nacional de Telecomunica\u00e7\u00f5es",
        "codigoOrgaoSuperior": "41000",
        "nomeOrgaoSuperior": "Minist\u00e9rio das Comunica\u00e7\u00f5es",
        "valor": 118750.0
    },
    {
        "anoMes": 202301,
        "codigoPessoa": "***.269.958-**",
        "nomePessoa": "CYNTHIA BORGES MOURANI",
        "tipoPessoa": "Pessoa F\u00edsica",
        "municipioPessoa": "ITUVERAVA",
        "siglaUFPessoa": "SP",
        "codigoUG": "242160",
        "nomeUG": "TELECOMUNICACOES BRASILEIRAS S/A",
        "codigoOrgao": "24216",
        "nomeOrgao": "Telecomunica\u00e7\u00f5es Brasileiras S.A.",
        "codigoOrgaoSuperior": "41000",
        "nomeOrgaoSuperior": "Minist\u00e9rio das Comunica\u00e7\u00f5es",
        "valor": 3252.38
    },
    {
        "anoMes": 202301,
        "codigoPessoa": "07.432.517/0001-07",
        "nomePessoa": "SIMPRESS COMERCIO LOCACAO E SERVICOS LTDA",
        "tipoPessoa": "Entidades Empresariais Privadas",
        "municipioPessoa": "SANTANA DE PARNA\u00cdBA",
        "siglaUFPessoa": "SP",
        "codigoUG": "410003",
        "nomeUG": "COORDENACAO-GERAL DE RECURSOS LOGISTICOS",
        "codigoOrgao": "41000",
        "nomeOrgao": "Minist\u00e9rio das Comunica\u00e7\u00f5es - Unidades com v\u00ednculo direto",
        "codigoOrgaoSuperior": "41000",
        "nomeOrgaoSuperior": "Minist\u00e9rio das Comunica\u00e7\u00f5es",
        "valor": 15089.35
    }
]